AUTHORS.rst
LICENSE.txt
MANIFEST.in
README.rst
ez_setup.py
setup.py
corral/__init__.py
corral/conf.py
corral/core.py
corral/creator.py
corral/docs.py
corral/exceptions.py
corral/qa.py
corral/setup.py
corral/util.py
corral/cli/__init__.py
corral/cli/base.py
corral/cli/commands.py
corral/db/__init__.py
corral/db/default_models.py
corral/libs/__init__.py
corral/libs/argparse_ext.py
corral/libs/django_integration.py
corral/libs/notebook_extension.py
corral/libs/sqlalchemy_sql_shell.py
corral/res/__init__.py
corral/res/doc.md
corral/res/logo-64x64.png
corral/res/qa_report.md
corral/run/__init__.py
corral/run/alert.py
corral/run/base.py
corral/run/endpoints.py
corral/run/loader.py
corral/run/step.py
corral/template/in_corral.py
corral/template/template/__init__.py
corral/template/template/alerts.py
corral/template/template/commands.py
corral/template/template/load.py
corral/template/template/models.py
corral/template/template/pipeline.py
corral/template/template/settings.py
corral/template/template/steps.py
corral/template/template/tests.py
corral/template/template/migrations/alembic.ini
corral/template/template/migrations/env.py
corral/template/template/migrations/script.py.mako
corral/template/template/migrations/versions/README.txt
corral_pipeline.egg-info/PKG-INFO
corral_pipeline.egg-info/SOURCES.txt
corral_pipeline.egg-info/dependency_links.txt
corral_pipeline.egg-info/entry_points.txt
corral_pipeline.egg-info/requires.txt
corral_pipeline.egg-info/top_level.txt