Metadata-Version: 1.1
Name: corral-pipeline
Version: 0.2.7
Summary: MVC framework for create trustworthy pipelines
Home-page: https://github.com/toros-astro/corral
Author: Cabral, Sanchez & Berois
Author-email: corral-users-forum@googlegroups.com
License: 3 Clause BSD
Keywords: pipeline etl sql rdbms mvc
Platform: UNKNOWN
Classifier: Development Status :: 4 - Beta
Classifier: Intended Audience :: Science/Research
Classifier: Intended Audience :: Developers
Classifier: License :: OSI Approved
Classifier: Operating System :: POSIX
Classifier: Operating System :: Unix
Classifier: Operating System :: MacOS
Classifier: Programming Language :: Python
Classifier: Programming Language :: Python :: 2
Classifier: Programming Language :: Python :: 2.7
Classifier: Programming Language :: Python :: 3
Classifier: Programming Language :: Python :: 3.4
Classifier: Programming Language :: Python :: 3.5
Classifier: Programming Language :: Python :: Implementation :: CPython
Classifier: Topic :: Scientific/Engineering
Classifier: Topic :: Software Development
